rebix_bitpin/__init__.py
rebix_bitpin/exceptions.py
rebix_bitpin/helpers.py
rebix_bitpin/main.py
rebix_bitpin-0.0.10.dist-info/METADATA
rebix_bitpin-0.0.10.dist-info/WHEEL
rebix_bitpin-0.0.10.dist-info/top_level.txt
rebix_bitpin-0.0.10.dist-info/RECORD
