Metadata-Version: 2.1
Name: rebix-bitpin
Version: 0.0.10
Summary: Bitpin cryptocurrency exchange python sdk
Home-page: https://github.com/Rebix/rebix-bitpin
Author: rebix
Author-email: cnashohrat@gmail.com
License: MIT
Project-URL: Bug Tracker, https://github.com/Rebix/rebix-bitpin/issues
Keywords: bitpin,crypto,exchange,API,SDK
Classifier: Development Status :: 3 - Alpha
Classifier: Intended Audience :: Developers
Classifier: Topic :: Software Development :: Build Tools
Classifier: License :: OSI Approved :: MIT License
Classifier: Programming Language :: Python :: 3
Classifier: Programming Language :: Python :: 3.4
Classifier: Programming Language :: Python :: 3.5
Classifier: Programming Language :: Python :: 3.6
Classifier: Programming Language :: Python :: 3.7
Classifier: Programming Language :: Python :: 3.8
Classifier: Programming Language :: Python :: 3.9
Requires-Python: >=3.6
Requires-Dist: requests
Requires-Dist: simplejson
Requires-Dist: nice-tools
